pydx/__init__.py
pydx/main.py
pydx/commands/__init__.py
pydx/common/__init__.py
developer_experience-0.1.1.dist-info/LICENSE.rst
developer_experience-0.1.1.dist-info/METADATA
developer_experience-0.1.1.dist-info/WHEEL
developer_experience-0.1.1.dist-info/entry_points.txt
developer_experience-0.1.1.dist-info/top_level.txt
developer_experience-0.1.1.dist-info/RECORD
