Metadata-Version: 2.1
Name: developer-experience
Version: 0.1.1
Summary: UNKNOWN
Home-page: UNKNOWN
License: BSD-3-Clause
Project-URL: Code, https://github.com/infosmith/pydx
Project-URL: Issue tracker, https://github.com/infosmith/pydx/issues
Platform: UNKNOWN
Classifier: Development Status :: 1 - Planning
Classifier: Environment :: Console
Classifier: Intended Audience :: Developers
Classifier: License :: OSI Approved :: BSD License
Classifier: Natural Language :: English
Classifier: Operating System :: MacOS
Classifier: Operating System :: POSIX
Classifier: Programming Language :: Python :: 3
Classifier: Programming Language :: Python :: 3.4
Classifier: Programming Language :: Python :: 3.5
Classifier: Programming Language :: Python :: 3.6
Classifier: Programming Language :: Python :: 3.7
Classifier: Programming Language :: Python :: 3.8
Classifier: Programming Language :: Python :: Implementation :: CPython
Requires-Python: >=3.4
